{
    "nombre": "Germán Sandoval",
    "email": "argentina@programa.com",
    "password": "1234",
    "profesion": "Desarrolladora Full Stack Jr.",
    "linkIn": "https://www.linkedin.com/in/leticia-portillo-b62ba3103/",
    "linkMail":"/contacto",
    "linkWP":"",
    "linkGH": "https://github.com/soyElSando",
    "linkIG":"https://instagram.com/ger.sando",
    "descripcionEs": "La diversidad en la formación, en el trabajo y en los intereses es algo pasado de moda. Hoy no está bien visto porque se tiende a pensar que se es 'poco especialista'. Sin embargo, es algo de mi persona que valoro mucho. Admito ante la mirada del lector que mi formación es diversa en distintas áreas. Cuando digo áreas diversas digo artes, electrónica, redes, administración y digo desarrollo de software (por supuesto).",
    "descripcionEn": "Diversity in training, work and interests is something out of fashion. Today it is not well seen because people tend to think that they are 'little specialists'. However, it is something of my person that I value a lot. I admit before the reader's gaze that my training is diverse in different areas. When I say diverse areas I say arts, electronics, networks, administration and I say software development (of course).",
    "avatar": "assets/gerSando.jpg"
}